{"type":"Events Per Year","rank_type":"OPEN","stats":[{"year":"2025","country_count":"1","tournament_count":"9680","player_count":"209880","stats_rank":1},{"year":"2024","country_count":"1","tournament_count":"10042","player_count":"221107","stats_rank":2},{"year":"2023","country_count":"1","tournament_count":"7965","player_count":"183449","stats_rank":3},{"year":"2022","country_count":"1","tournament_count":"5627","player_count":"125700","stats_rank":4},{"year":"2021","country_count":"1","tournament_count":"1747","player_count":"37067","stats_rank":5},{"year":"2020","country_count":"1","tournament_count":"1154","player_count":"25138","stats_rank":6},{"year":"2019","country_count":"1","tournament_count":"5420","player_count":"117766","stats_rank":7},{"year":"2018","country_count":"1","tournament_count":"4071","player_count":"88690","stats_rank":8},{"year":"2017","country_count":"1","tournament_count":"3332","player_count":"73758","stats_rank":9},{"year":"2016","country_count":"1","tournament_count":"2494","player_count":"61885","stats_rank":10}]}
